{
  "Comment": "Orquestrador principal v1 da plataforma de ingestao.",
  "StartAt": "NormalizeInput",
  "States": {
    "NormalizeInput": {
      "Type": "Pass",
      "Parameters": {
        "meta": {
          "executionId.$": "$$.Execution.Id",
          "stateMachineId.$": "$$.StateMachine.Id",
          "startedAt.$": "$$.Execution.StartTime",
          "trigger.$": "$.trigger",
          "source.$": "$.source",
          "stage.$": "$.stage",
          "service.$": "$.service"
        },
        "schedulerInput": {
          "now.$": "$.now"
        }
      },
      "ResultPath": "$",
      "Next": "Scheduler"
    },
    "Scheduler": {
      "Type": "Task",
      "Resource": {
        "Fn::GetAtt": ["SchedulerLambdaFunction", "Arn"]
      },
      "Parameters": {
        "now.$": "$.schedulerInput.now",
        "meta.$": "$.meta"
      },
      "Retry": [
        {
          "ErrorEquals": [
            "Lambda.ServiceException",
            "Lambda.AWSLambdaException",
            "Lambda.SdkClientException",
            "Lambda.TooManyRequestsException"
          ],
          "IntervalSeconds": 2,
          "MaxAttempts": 3,
          "BackoffRate": 2
        },
        {
          "ErrorEquals": ["States.Timeout"],
          "IntervalSeconds": 5,
          "MaxAttempts": 2,
          "BackoffRate": 2
        }
      ],
      "ResultPath": "$.schedulerResult",
      "Next": "ProcessEligibleSources",
      "Catch": [
        {
          "ErrorEquals": ["States.ALL"],
          "ResultPath": "$.schedulerError",
          "Next": "BuildSchedulerFailureOutput"
        }
      ]
    },
    "ProcessEligibleSources": {
      "Type": "Map",
      "ItemsPath": "$.schedulerResult.sources",
      "MaxConcurrencyPath": "$.schedulerResult.maxConcurrency",
      "Parameters": {
        "sourceId.$": "$$.Map.Item.Value.sourceId",
        "tenantId.$": "$$.Map.Item.Value.tenantId",
        "meta": {
          "executionId.$": "$.meta.executionId",
          "stateMachineId.$": "$.meta.stateMachineId",
          "startedAt.$": "$.meta.startedAt",
          "trigger.$": "$.meta.trigger",
          "source.$": "$.meta.source",
          "stage.$": "$.meta.stage",
          "service.$": "$.meta.service",
          "traceContext.$": "$.schedulerResult.traceContext"
        }
      },
      "Iterator": {
        "StartAt": "InvokeCollector",
        "States": {
          "InvokeCollector": {
            "Type": "Task",
            "Resource": {
              "Fn::GetAtt": ["CollectorLambdaFunction", "Arn"]
            },
            "Parameters": {
              "sourceId.$": "$.sourceId",
              "tenantId.$": "$.tenantId",
              "meta.$": "$.meta"
            },
            "Retry": [
              {
                "ErrorEquals": [
                  "Lambda.ServiceException",
                  "Lambda.AWSLambdaException",
                  "Lambda.SdkClientException",
                  "Lambda.TooManyRequestsException"
                ],
                "IntervalSeconds": 2,
                "MaxAttempts": 3,
                "BackoffRate": 2
              },
              {
                "ErrorEquals": ["States.Timeout"],
                "IntervalSeconds": 5,
                "MaxAttempts": 2,
                "BackoffRate": 2
              }
            ],
            "Catch": [
              {
                "ErrorEquals": ["States.ALL"],
                "ResultPath": "$.collectorError",
                "Next": "BuildItemFailureResult"
              }
            ],
            "ResultPath": "$.collectorResult",
            "Next": "BuildItemSuccessResult"
          },
          "BuildItemSuccessResult": {
            "Type": "Pass",
            "Parameters": {
              "result": {
                "sourceId.$": "$.sourceId",
                "tenantId.$": "$.tenantId",
                "status": "SUCCEEDED",
                "processedAt.$": "$.collectorResult.processedAt",
                "recordsSent.$": "$.collectorResult.recordsSent"
              },
              "metric": {
                "stage.$": "$.meta.stage",
                "executionId.$": "$.meta.executionId",
                "sourceId.$": "$.sourceId"
              }
            },
            "Next": "PublishItemSuccessMetric"
          },
          "PublishItemSuccessMetric": {
            "Type": "Task",
            "Resource": "arn:aws:states:::aws-sdk:cloudwatch:putMetricData",
            "Parameters": {
              "Namespace": "AlertOrchestrationService/Orchestration",
              "MetricData": [
                {
                  "MetricName": "SourceProcessed",
                  "Dimensions": [
                    {
                      "Name": "Stage",
                      "Value.$": "$.metric.stage"
                    }
                  ],
                  "Unit": "Count",
                  "Value": 1
                },
                {
                  "MetricName": "SourceProcessedBySource",
                  "Dimensions": [
                    {
                      "Name": "Stage",
                      "Value.$": "$.metric.stage"
                    },
                    {
                      "Name": "ExecutionId",
                      "Value.$": "$.metric.executionId"
                    },
                    {
                      "Name": "SourceId",
                      "Value.$": "$.metric.sourceId"
                    }
                  ],
                  "Unit": "Count",
                  "Value": 1
                }
              ]
            },
            "Next": "ReturnItemSuccessResult",
            "Catch": [
              {
                "ErrorEquals": ["States.ALL"],
                "ResultPath": "$.metricPublishError",
                "Next": "ReturnItemSuccessResult"
              }
            ]
          },
          "ReturnItemSuccessResult": {
            "Type": "Pass",
            "Parameters": {
              "sourceId.$": "$.result.sourceId",
              "tenantId.$": "$.result.tenantId",
              "status.$": "$.result.status",
              "processedAt.$": "$.result.processedAt",
              "recordsSent.$": "$.result.recordsSent"
            },
            "End": true
          },
          "BuildItemFailureResult": {
            "Type": "Pass",
            "Parameters": {
              "result": {
                "sourceId.$": "$.sourceId",
                "tenantId.$": "$.tenantId",
                "status": "FAILED",
                "error.$": "$.collectorError.Error",
                "cause.$": "$.collectorError.Cause"
              },
              "metric": {
                "stage.$": "$.meta.stage",
                "executionId.$": "$.meta.executionId",
                "sourceId.$": "$.sourceId"
              }
            },
            "Next": "PublishItemFailureMetric"
          },
          "PublishItemFailureMetric": {
            "Type": "Task",
            "Resource": "arn:aws:states:::aws-sdk:cloudwatch:putMetricData",
            "Parameters": {
              "Namespace": "AlertOrchestrationService/Orchestration",
              "MetricData": [
                {
                  "MetricName": "SourceFailed",
                  "Dimensions": [
                    {
                      "Name": "Stage",
                      "Value.$": "$.metric.stage"
                    }
                  ],
                  "Unit": "Count",
                  "Value": 1
                },
                {
                  "MetricName": "SourceFailedBySource",
                  "Dimensions": [
                    {
                      "Name": "Stage",
                      "Value.$": "$.metric.stage"
                    },
                    {
                      "Name": "ExecutionId",
                      "Value.$": "$.metric.executionId"
                    },
                    {
                      "Name": "SourceId",
                      "Value.$": "$.metric.sourceId"
                    }
                  ],
                  "Unit": "Count",
                  "Value": 1
                }
              ]
            },
            "Next": "ReturnItemFailureResult",
            "Catch": [
              {
                "ErrorEquals": ["States.ALL"],
                "ResultPath": "$.metricPublishError",
                "Next": "ReturnItemFailureResult"
              }
            ]
          },
          "ReturnItemFailureResult": {
            "Type": "Pass",
            "Parameters": {
              "sourceId.$": "$.result.sourceId",
              "tenantId.$": "$.result.tenantId",
              "status.$": "$.result.status",
              "error.$": "$.result.error",
              "cause.$": "$.result.cause"
            },
            "End": true
          }
        }
      },
      "ResultPath": "$.collectorResults",
      "Next": "BuildExecutionOutput"
    },
    "BuildExecutionOutput": {
      "Type": "Pass",
      "Parameters": {
        "meta.$": "$.meta",
        "sources.$": "$.schedulerResult.sources",
        "results.$": "$.collectorResults",
        "scheduler": {
          "contractVersion.$": "$.schedulerResult.contractVersion",
          "referenceNow.$": "$.schedulerResult.referenceNow",
          "hasEligibleSources.$": "$.schedulerResult.hasEligibleSources"
        },
        "summary": {
          "processedSources.$": "States.ArrayLength($.collectorResults)",
          "eligibleSources.$": "$.schedulerResult.eligibleSources",
          "generatedAt.$": "$.schedulerResult.generatedAt",
          "maxConcurrency.$": "$.schedulerResult.maxConcurrency",
          "schedulerStatus": "SUCCEEDED"
        }
      },
      "ResultPath": "$",
      "Next": "PublishExecutionSuccessMetric"
    },
    "PublishExecutionSuccessMetric": {
      "Type": "Task",
      "Resource": "arn:aws:states:::aws-sdk:cloudwatch:putMetricData",
      "Parameters": {
        "Namespace": "AlertOrchestrationService/Orchestration",
        "MetricData": [
          {
            "MetricName": "ExecutionSucceeded",
            "Dimensions": [
              {
                "Name": "Stage",
                "Value.$": "$.meta.stage"
              }
            ],
            "Unit": "Count",
            "Value": 1
          },
          {
            "MetricName": "ExecutionSucceededByExecution",
            "Dimensions": [
              {
                "Name": "Stage",
                "Value.$": "$.meta.stage"
              },
              {
                "Name": "ExecutionId",
                "Value.$": "$.meta.executionId"
              }
            ],
            "Unit": "Count",
            "Value": 1
          },
          {
            "MetricName": "ProcessedSources",
            "Dimensions": [
              {
                "Name": "Stage",
                "Value.$": "$.meta.stage"
              }
            ],
            "Unit": "Count",
            "Value.$": "$.summary.processedSources"
          },
          {
            "MetricName": "EligibleSources",
            "Dimensions": [
              {
                "Name": "Stage",
                "Value.$": "$.meta.stage"
              }
            ],
            "Unit": "Count",
            "Value.$": "$.summary.eligibleSources"
          }
        ]
      },
      "Next": "Done",
      "Catch": [
        {
          "ErrorEquals": ["States.ALL"],
          "ResultPath": "$.metricPublishError",
          "Next": "Done"
        }
      ]
    },
    "BuildSchedulerFailureOutput": {
      "Type": "Pass",
      "Parameters": {
        "meta.$": "$.meta",
        "sources": [],
        "results": [],
        "summary": {
          "processedSources": 0,
          "eligibleSources": 0,
          "schedulerStatus": "FAILED",
          "error.$": "$.schedulerError.Error",
          "cause.$": "$.schedulerError.Cause"
        }
      },
      "ResultPath": "$",
      "Next": "PublishExecutionFailureMetric"
    },
    "PublishExecutionFailureMetric": {
      "Type": "Task",
      "Resource": "arn:aws:states:::aws-sdk:cloudwatch:putMetricData",
      "Parameters": {
        "Namespace": "AlertOrchestrationService/Orchestration",
        "MetricData": [
          {
            "MetricName": "ExecutionFailed",
            "Dimensions": [
              {
                "Name": "Stage",
                "Value.$": "$.meta.stage"
              }
            ],
            "Unit": "Count",
            "Value": 1
          },
          {
            "MetricName": "ExecutionFailedByExecution",
            "Dimensions": [
              {
                "Name": "Stage",
                "Value.$": "$.meta.stage"
              },
              {
                "Name": "ExecutionId",
                "Value.$": "$.meta.executionId"
              }
            ],
            "Unit": "Count",
            "Value": 1
          }
        ]
      },
      "Next": "SchedulerFailed",
      "Catch": [
        {
          "ErrorEquals": ["States.ALL"],
          "ResultPath": "$.metricPublishError",
          "Next": "SchedulerFailed"
        }
      ]
    },
    "SchedulerFailed": {
      "Type": "Fail",
      "Error": "SchedulerStepFailed",
      "Cause": "Scheduler task failed before Map state execution."
    },
    "Done": {
      "Type": "Succeed"
    }
  }
}
